openfast_io/FAST_linearization_reader.py
openfast_io/FAST_output_reader.py
openfast_io/FAST_post.py
openfast_io/FAST_reader.py
openfast_io/FAST_vars_out.py
openfast_io/FAST_writer.py
openfast_io/FileTools.py
openfast_io/StC_defaults.py
openfast_io/_version.py
openfast_io/create_output_vars.py
openfast_io/turbsim_file.py
openfast_io/turbsim_util.py
openfast_io/tests/conftest.py
openfast_io/tests/test_of_io_pytest.py
openfast_io-4.1.2.dist-info/METADATA
openfast_io-4.1.2.dist-info/WHEEL
openfast_io-4.1.2.dist-info/RECORD
