Metadata-Version: 2.4
Name: openfast_io
Version: 4.1.2
Summary: Readers and writers for OpenFAST files.
Project-URL: homepage, https://github.com/OpenFAST/openfast
Project-URL: documentation, https://openfast.readthedocs.io/en/main/
Project-URL: repository, https://github.com/OpenFAST/openfast
Project-URL: Issues, https://github.com/OpenFAST/openfast/issues
Author-email: Mayank Chetan <mayank.chetan@nrel.gov>, Andy Platt <andy.platt@nrel.gov>, Derek Slaughter <derek.slaughter@nrel.gov>, NREL WISDEM Team <systems.engineering@nrel.gov>
Maintainer-email: Mayank Chetan <mayank.chetan@nrel.gov>, Andy Platt <andy.platt@nrel.gov>, Derek Slaughter <derek.slaughter@nrel.gov>
License:                                  Apache License
Classifier: Development Status :: 4 - Beta
Classifier: Intended Audience :: Science/Research
Classifier: License :: OSI Approved :: Apache Software License
Classifier: Operating System :: OS Independent
Classifier: Programming Language :: Python :: 3 :: Only
Classifier: Programming Language :: Python :: 3.10
Classifier: Programming Language :: Python :: 3.11
Classifier: Programming Language :: Python :: 3.12
Classifier: Topic :: Scientific/Engineering
Requires-Python: >3.10
Requires-Dist: deepdiff>8.0
Requires-Dist: numpy>1.0
Requires-Dist: pandas>2.0
Requires-Dist: ruamel-yaml>0.18
Provides-Extra: all
Requires-Dist: rosco>2.9.2; extra == 'all'
Requires-Dist: xlrd>2; extra == 'all'
Provides-Extra: rosco
Requires-Dist: rosco>2.9.2; extra == 'rosco'
Provides-Extra: xlrd
Requires-Dist: xlrd>2; extra == 'xlrd'
